LICENSE
MANIFEST.in
README.md
setup.py
gmbinder/__init__.py
gmbinder/api.py
gmbinder/auth.py
gmbinder/cli.py
gmbinder/printing.py
gmbinder.egg-info/PKG-INFO
gmbinder.egg-info/SOURCES.txt
gmbinder.egg-info/dependency_links.txt
gmbinder.egg-info/entry_points.txt
gmbinder.egg-info/requires.txt
gmbinder.egg-info/top_level.txt